paw/__init__.py
paw/cli.py
paw/paw_ecdict.py
paw/paw_jlpt.py
paw/paw_mecab.py
paw/paw_server.py
emacs_paw-0.1.20.dist-info/METADATA
emacs_paw-0.1.20.dist-info/WHEEL
emacs_paw-0.1.20.dist-info/entry_points.txt
emacs_paw-0.1.20.dist-info/top_level.txt
emacs_paw-0.1.20.dist-info/RECORD
