Metadata-Version: 2.4
Name: emacs-paw
Version: 0.1.20
Summary: Study for a life in Emacs with advanced annotation and language learning tools.
Author: Damon Chan
Project-URL: Homepage, https://github.com/chenyanming/paw
Project-URL: Repository, https://github.com/chenyanming/paw
Keywords: Emacs,annotation,language learning,dictionary,sql,org-mode
Classifier: Development Status :: 3 - Alpha
Classifier: Intended Audience :: Developers
Classifier: License :: OSI Approved :: GNU General Public License v3 (GPLv3)
Classifier: Programming Language :: Python :: 3.10
Classifier: Programming Language :: Python :: 3.11
Classifier: Natural Language :: English
Classifier: Natural Language :: Japanese
Classifier: Operating System :: OS Independent
Requires-Python: >=3.10
Requires-Dist: waitress
Requires-Dist: Flask
Requires-Dist: flask-cors
Requires-Dist: requests
Requires-Dist: nltk
Requires-Dist: mecab-python3
Requires-Dist: unidic-lite
Requires-Dist: janome
Requires-Dist: lingua-language-detector
